{"Warranty Terms - Parts":{"Name":"Warranty Terms - Parts","Value":"3 years limited: hardware","NameForDisplay":"Warranty Terms - Parts","CanDiff":true},"Warranty Terms - Labor":{"Name":"Warranty Terms - Labor","Value":"3 years limited: hardware","NameForDisplay":"Warranty Terms - Labor","CanDiff":true},"Product Height":{"Name":"Product Height","Value":"9\"","NameForDisplay":"Product Height","CanDiff":true},"Product Width":{"Name":"Product Width","Value":"4.7\"","NameForDisplay":"Product Width","CanDiff":true},"Product Weight":{"Name":"Product Weight","Value":"6.6 oz.","NameForDisplay":"Product Weight","CanDiff":true},"Product Depth":{"Name":"Product Depth","Value":"2.3\"","NameForDisplay":"Product Depth","CanDiff":true},"Scrolling Wheel":{"Name":"Scrolling Wheel","Value":"Yes","NameForDisplay":"Scrolling Wheel","CanDiff":true},"Tilt Wheel":{"Name":"Tilt Wheel","Value":"Yes","NameForDisplay":"Tilt Wheel","CanDiff":true},"Optical Technology":{"Name":"Optical Technology","Value":"No","NameForDisplay":"Optical Technology","CanDiff":true},"Zooming Capabilities":{"Name":"Zooming Capabilities","Value":"Yes","NameForDisplay":"Zooming Capabilities","CanDiff":true},"Ergonomic":{"Name":"Ergonomic","Value":"Yes","NameForDisplay":"Ergonomic","CanDiff":true},"Left/Right-Handed Design":{"Name":"Left/Right-Handed Design","Value":"Ambidextrous","NameForDisplay":"Left/Right-Handed Design","CanDiff":true},"Cordless/Wireless":{"Name":"Cordless/Wireless","Value":"Yes","NameForDisplay":"Cordless/Wireless","CanDiff":true},"Batteries Needed":{"Name":"Batteries Needed","Value":"Yes","NameForDisplay":"Batteries Needed","CanDiff":true},"Battery Type":{"Name":"Battery Type","Value":"AA","NameForDisplay":"Battery Type","CanDiff":true},"Battery Quantity":{"Name":"Battery Quantity","Value":"2","NameForDisplay":"Battery Quantity","CanDiff":true},"Battery Included":{"Name":"Battery Included","Value":"Yes","NameForDisplay":"Battery Included","CanDiff":true},"Battery Indicator":{"Name":"Battery Indicator","Value":"No","NameForDisplay":"Battery Indicator","CanDiff":true},"Programmable Buttons":{"Name":"Programmable Buttons","Value":"Yes","NameForDisplay":"Programmable Buttons","CanDiff":true},"Number of Buttons":{"Name":"Number of Buttons","Value":"4 + scroll wheel button","NameForDisplay":"Number of Buttons","CanDiff":true},"Power Switch":{"Name":"Power Switch","Value":"Yes","NameForDisplay":"Power Switch","CanDiff":true},"Type of Pointing Device":{"Name":"Type of Pointing Device","Value":"Laser mouse","NameForDisplay":"Type of Pointing Device","CanDiff":true},"Connection Type":{"Name":"Connection Type","Value":"Wireless USB","NameForDisplay":"Connection Type","CanDiff":true},"Port Connection":{"Name":"Port Connection","Value":"USB","NameForDisplay":"Port Connection","CanDiff":true},"System Requirements":{"Name":"System Requirements","Value":"Windows XP or Vista; Mac OS X 10.3.9 or later","NameForDisplay":"System Requirements","CanDiff":true},"UPC":{"Name":"UPC","Value":"097855066596","NameForDisplay":"UPC","CanDiff":true}}